ib_insync/__init__.py
ib_insync/client.py
ib_insync/connection.py
ib_insync/contract.py
ib_insync/decoder.py
ib_insync/flexreport.py
ib_insync/ib.py
ib_insync/ibcontroller.py
ib_insync/objects.py
ib_insync/order.py
ib_insync/py.typed
ib_insync/ticker.py
ib_insync/util.py
ib_insync/version.py
ib_insync/wrapper.py
ib_insync-0.9.86.dist-info/LICENSE
ib_insync-0.9.86.dist-info/METADATA
ib_insync-0.9.86.dist-info/WHEEL
ib_insync-0.9.86.dist-info/top_level.txt
ib_insync-0.9.86.dist-info/RECORD
